examples/basic_usage.py
examples/cl_sequence.py
examples/four_agents.py
experiments/__init__.py
experiments/ippo.py
experiments/mappo.py
experiments/utils.py
experiments/continual/agem.py
experiments/continual/base.py
experiments/continual/cbp.py
experiments/continual/ewc.py
experiments/continual/ft.py
experiments/continual/l2.py
experiments/continual/mas.py
experiments/continual/packnet.py
experiments/evaluation/__init__.py
experiments/evaluation/evaluator.py
experiments/experimental/ippo_cbp.py
experiments/experimental/ippo_eval.py
experiments/experimental/ippo_fast.py
experiments/experimental/ippo_packnet.py
experiments/experimental/utils_vdn.py
experiments/experimental/vdn.py
experiments/model/cbp_actorcritic.py
experiments/model/cnn.py
experiments/model/decoupled_mlp.py
experiments/model/mlp.py
experiments/model/q_cnn.py
experiments/model/q_mlp.py
experiments/partner_adaptation/__init__.py
experiments/partner_adaptation/run_br.py
experiments/partner_adaptation/train_br.py
experiments/partner_adaptation/train_ego.py
experiments/partner_adaptation/partner_agents/__init__.py
experiments/partner_adaptation/partner_agents/agent_interface.py
experiments/partner_adaptation/partner_agents/mlp_actor_critic.py
experiments/partner_adaptation/partner_agents/population_interface.py
experiments/partner_adaptation/partner_agents/overcooked/__init__.py
experiments/partner_adaptation/partner_agents/overcooked/agent_policy_wrappers.py
experiments/partner_adaptation/partner_agents/overcooked/base_agent.py
experiments/partner_adaptation/partner_agents/overcooked/independent_agent.py
experiments/partner_adaptation/partner_agents/overcooked/onion_agent.py
experiments/partner_adaptation/partner_agents/overcooked/plate_agent.py
experiments/partner_adaptation/partner_agents/overcooked/random_agent.py
experiments/partner_adaptation/partner_agents/overcooked/static_agent.py
experiments/partner_adaptation/partner_generation/BRDiv.py
MEAL_Bench-0.1.0.dist-info/LICENSE
MEAL_Bench-0.1.0.dist-info/METADATA
MEAL_Bench-0.1.0.dist-info/WHEEL
MEAL_Bench-0.1.0.dist-info/top_level.txt
MEAL_Bench-0.1.0.dist-info/RECORD
