Metadata-Version: 2.1
Name: MEAL-Bench
Version: 0.1.0
Summary: MEAL: A Benchmark for Continual Multi-Agent Reinforcement Learning
Author-email: Tristan Tomilin <tristan.tomilin@hotmail.com>
License: MIT
Project-URL: Homepage, https://github.com/TTomilin/MEAL
Classifier: Programming Language :: Python :: 3
Classifier: Programming Language :: Python :: 3.10
Classifier: License :: OSI Approved :: MIT License
Classifier: Operating System :: OS Independent
Classifier: Topic :: Scientific/Engineering :: Artificial Intelligence
Requires-Python: >=3.10
License-File: LICENSE
Requires-Dist: jax
Requires-Dist: flax
Requires-Dist: chex
Requires-Dist: gymnax
Requires-Dist: tyro
Requires-Dist: distrax
Requires-Dist: tensorboard
Requires-Dist: tensorboardX
Requires-Dist: wandb
Requires-Dist: pyyaml
Provides-Extra: utils
Requires-Dist: optax ; extra == 'utils'
Requires-Dist: numpy ; extra == 'utils'
Requires-Dist: tqdm ; extra == 'utils'
Requires-Dist: pandas ; extra == 'utils'
Requires-Dist: orbax-checkpoint ; extra == 'utils'
Requires-Dist: pytest ; extra == 'utils'
Provides-Extra: viz
Requires-Dist: scipy ; extra == 'viz'
Requires-Dist: imageio ; extra == 'viz'
Requires-Dist: pygame ; extra == 'viz'
Requires-Dist: matplotlib ; extra == 'viz'
Requires-Dist: pillow ; extra == 'viz'
Requires-Dist: seaborn ; extra == 'viz'
Requires-Dist: ipython ; extra == 'viz'
Requires-Dist: ipywidgets ; extra == 'viz'
